{"F1": {"id": 1, "nombre": "FarmaHospital", "abreviatura": "FH", "estado": "Activo"}, "F2": {"id": 2, "nombre": "Farmacia Fuerzas Armadas", "abreviatura": "FFA", "estado": "Activo"}, "F3": {"id": 3, "nombre": "Farmacia Fuerzas Armadas 2", "abreviatura": "FFA2", "estado": "Activo"}, "F4": {"id": 4, "nombre": "Farma Expres", "abreviatura": "FE", "estado": "Inactivo"}, "F5": {"id": 5, "nombre": "FarmaSur", "abreviatura": "FS", "estado": "Inactivo"}, "F6": {"id": 6, "nombre": "Farmacia +Ahorro", "abreviatura": "F+A", "estado": "Inactivo"}}